yamlparser/__init__.py
yamlparser/namespace.py
yamlparser/parser.py
yamlparser/registry.py
yamlparser-0.2.3.dist-info/LICENSE
yamlparser-0.2.3.dist-info/METADATA
yamlparser-0.2.3.dist-info/WHEEL
yamlparser-0.2.3.dist-info/top_level.txt
yamlparser-0.2.3.dist-info/RECORD
