Metadata-Version: 2.1
Name: yamlparser
Version: 0.2.3
Summary: A Package to combine YAML configurations and argument parsing
Author-email: Manuel Guenther <siebenkopf@googlemail.com>
Project-URL: Homepage, https://github.com/AIML-IfI/yamlparser
Project-URL: Bug Tracker, https://github.com/AIML-IfI/yamlparser/issues
Classifier: Programming Language :: Python :: 3
Classifier: License :: OSI Approved :: MIT License
Classifier: Operating System :: OS Independent
Requires-Python: >=3.7
License-File: LICENSE
Requires-Dist: argparse
Requires-Dist: pyyaml
